pykv/__init__.py
pykv/main.py
pykv-0.1.0.dist-info/LICENSE
pykv-0.1.0.dist-info/METADATA
pykv-0.1.0.dist-info/WHEEL
pykv-0.1.0.dist-info/top_level.txt
pykv-0.1.0.dist-info/RECORD
