Metadata-Version: 2.1
Name: pykv
Version: 0.1.0
Summary: A key-value storage in the memory, it is simple and fast.
Home-page: https://github.com/skyline93/pykv
Author: skyline93
Author-email: glf9832@163.com
License: MIT
Platform: UNKNOWN
Requires-Python: >=3.8
